{
  "id": "1002",
  "title": "救命！周五下午5:50被叫开会？本“淡人”反手就是一个AI假笑翻译！",
  "author": "首席偷懒官",
  "content": "## 把情绪劳动外包给 AI\n\n每到周五下午 5:50，你是不是都要经历这种“工伤”：\n1. 已经开始在心里涮火锅了，微信群突然震动。\n2. 老板一句“大家来会议室碰一下”，瞬间让你破防。\n3. 想拒绝却怕显得不专业，想发火却只能回个“好的”。\n\n### 职场假笑翻译官：你的“数字避风港”\n\n与其在那儿内耗纠结，不如直接把这段“施法口诀”丢给 AI。它能瞬间把你的愤怒包装成最体面的职场艺术。\n\n**你可以直接复制这段提示词（Prompt）：**\n\n> **角色设定**：你现在是顶级“职场假笑翻译官”，擅长在不卑不亢的前提下，将负面情绪转化为高情商的专业职场表达。\n>\n> **你的职责**：\n> - **情绪外包**：接收我发给你的“大白话”或“愤怒原声”。\n> - **黑话重塑**：将其翻译成得体、体面、且能有效守护个人边界的职场沟通术语。\n> - **核心原则**：不接受无意义加塞，但听起来又极其专业且负责。\n>\n> **当前挑战**：老板周五下午 5:50 突然要求线下开会。\n> **我的真心话**：“我约了火锅，天王老子来了我也不开会，有什么事非要现在说？大家不回家了吗？”\n>\n> **请根据上述真心话，生成 3 种不同风格的回复内容**：\n> - **风格 A (温和推脱型)**：强调已有外部安排，建议文字沟通。\n> - **风格 B (专业高冷型)**：强调时间成本与产出比，建议延后。\n> - **风格 C (积极废话型)**：听起来很支持，但实际上本人不到场。\n\n### 它会如何帮你“偷懒”？\n\n* **情绪隔离**：你只负责发泄，AI 负责得体。你不需要花一秒钟去字斟句酌。 \n* **体面拒绝**：比如风格 A 的翻译结果：“目前该时段已有重要的外部协同安排，为确保会议产出质量，建议申请文字纪要并延后讨论。”\n\n> **偷懒建议：** \n> 当你按下发送键的那一刻，你的情绪已经闭环了。至于剩下的会议逻辑，交给 AI 去总结。你只需要穿上外套，理直气壮地走向那顿火锅。这才是科技带给打工人最真实的“体面”。\n\n```text\n咒语：\n“假笑留给你，火锅留给我。”\n```",
  "related_ids": ["1001", "1003"]
}